rccn_gen/LICENSE
rccn_gen/__init__.py
rccn_gen/systems.py
rccn_gen/utils.py
rccn_gen/text_modules/cargo_toml/cargo.txt
rccn_gen/text_modules/command/command.txt
rccn_gen/text_modules/command/command_module_enum.txt
rccn_gen/text_modules/command/command_module_struct.txt
rccn_gen/text_modules/main/main.txt
rccn_gen/text_modules/main/service_module_import_service.txt
rccn_gen/text_modules/main/service_module_mod_service.txt
rccn_gen/text_modules/main/service_module_register_service.txt
rccn_gen/text_modules/mod/mod.txt
rccn_gen/text_modules/service/command_module_match_cmd.txt
rccn_gen/text_modules/service/service.txt
rccn_gen/text_modules/telemetry/telemetry.txt
rccn_gen-1.3.3.dist-info/METADATA
rccn_gen-1.3.3.dist-info/WHEEL
rccn_gen-1.3.3.dist-info/RECORD
