Metadata-Version: 2.4
Name: rccn_gen
Version: 1.3.3
Summary: A python based generator for RACCOON OS source files in Rust from yamcs-pymdb config files.
Project-URL: Homepage, https://gitlab.com/rccn/pymdb_code_generation
Project-URL: Issues, https://gitlab.com/rccn/pymdb_code_generation/issues
Author-email: Fabian Krech <f.krech@tu-berlin.de>
License-Expression: GPL-3.0
Classifier: Operating System :: OS Independent
Classifier: Programming Language :: Python :: 3
Requires-Python: >=3.12
Requires-Dist: case-converter>=1.2.0
Requires-Dist: inflect>=7.5.0
Requires-Dist: yamcs-pymdb>=0.1.0
